examples/__init__.py
plbuilder/__init__.py
plbuilder/autoreloader.py
plbuilder/builder.py
plbuilder/cli.py
plbuilder/config.py
plbuilder/creator.py
plbuilder/init.py
plbuilder/paths.py
plbuilder/templater.py
plbuilder/templates/__init__.py
plbuilder/templates/always_body.j2
plbuilder/templates/always_imports.j2
plbuilder/templates/author.j2
plbuilder/templates/document.j2
plbuilder/templates/document_build.j2
plbuilder/templates/document_config.j2
plbuilder/templates/organization.j2
plbuilder/templates/presentation.j2
plbuilder/templates/presentation_build.j2
plbuilder/templates/presentation_config.j2
tests/__init__.py
tests/config.py
tests/dirutils.py
tests/fileutils.py
tests/generate.py
tests/projutils.py
tests/test_build.py
tests/test_create.py
tests/test_init_project.py
pl_builder-1.2.0.dist-info/LICENSE.md
pl_builder-1.2.0.dist-info/METADATA
pl_builder-1.2.0.dist-info/WHEEL
pl_builder-1.2.0.dist-info/entry_points.txt
pl_builder-1.2.0.dist-info/top_level.txt
pl_builder-1.2.0.dist-info/RECORD
