Metadata-Version: 2.1
Name: pl-builder
Version: 1.2.0
Summary: Pyexlatex Document Building Framework
Home-page: https://github.com/nickderobertis/pl-builder
Author: Nick DeRobertis
Author-email: whoopnip@gmail.com
License: MIT
Project-URL: Code, https://github.com/nickderobertis/pl-builder
Project-URL: Documentation, https://nickderobertis.github.io/pl-builder
Classifier: Development Status :: 3 - Alpha
Classifier: Intended Audience :: Developers
Classifier: Programming Language :: Python :: 3.6
Classifier: Programming Language :: Python :: 3.7
License-File: LICENSE.md
Requires-Dist: pyexlatex
Requires-Dist: fire
Requires-Dist: watchdog
Requires-Dist: jinja2
Requires-Dist: pydantic >=2
